LICENSE
README.md
setup.py
eden/__init__.py
eden/_version.py
eden/graph.py
eden/iterated_maximum_subarray.py
eden/sequence.py
eden/util.py
eden/display/__init__.py
eden/display/graph_layout.py
eden/io/__init__.py
eden/io/gspan.py
eden/io/node_link_data.py
eden/io/sequence.py
eden/io/word_sequence.py
eden/ml/__init__.py
eden/ml/estimator.py
eden/ml/estimator_utils.py
eden/ml/link_prediction.py
eden/ml/link_prediction_utils.py
eden/ml/ml.py
eden_kernel.egg-info/PKG-INFO
eden_kernel.egg-info/SOURCES.txt
eden_kernel.egg-info/dependency_links.txt
eden_kernel.egg-info/requires.txt
eden_kernel.egg-info/top_level.txt